sortorder/el.py
sortorder/eo.py
sortorder/ja.py
sortorder/ru.py
sortorder/__init__.py
sortorder/doc/conf.py
sortorder/doc/index.rst
sortorder/doc/make.bat
sortorder/doc/Makefile
sortorder/doc/module_el.rst
sortorder/doc/module_eo.rst
sortorder/doc/module_init.rst
sortorder/doc/module_ja.rst
sortorder/doc/module_ru.rst
sortorder/doc/README.rst
sortorder/doc/README_ja.rst
sortorder-2.0.6.dist-info/DESCRIPTION.rst
sortorder-2.0.6.dist-info/METADATA
sortorder-2.0.6.dist-info/metadata.json
sortorder-2.0.6.dist-info/RECORD
sortorder-2.0.6.dist-info/top_level.txt
sortorder-2.0.6.dist-info/WHEEL
