Metadata-Version: 2.0
Name: sortorder
Version: 2.0.6
Summary: Enable Sphinx to generate HTML5 valid files
Home-page: http://h12u.com/sphinx/html5_basic_theme/
Author: Suzumizaki-Kimitaka(鈴見咲 君高)
Author-email: info@h12u.com
License: BSD
Platform: any
Classifier: Development Status :: 5 - Production/Stable
Classifier: Environment :: Console
Classifier: Environment :: Web Environment
Classifier: Framework :: Sphinx
Classifier: Framework :: Sphinx :: Extension
Classifier: Intended Audience :: Developers
Classifier: Intended Audience :: Education
Classifier: License :: OSI Approved :: BSD License
Classifier: Operating System :: OS Independent
Classifier: Programming Language :: Python
Classifier: Programming Language :: Python :: 2
Classifier: Programming Language :: Python :: 3
Classifier: Topic :: Documentation
Classifier: Topic :: Documentation :: Sphinx
Classifier: Topic :: Text Processing
Classifier: Topic :: Utilities
Requires-Dist: sphinx (>=1.3)
